{"version":"0.0.0","commands":{"init":{"id":"init","description":"Generates a new specter.json and assign token in it.","pluginName":"specter","pluginType":"core","aliases":[],"flags":{"token":{"name":"token","type":"option","char":"t","description":"token to save"}},"args":[]},"server":{"id":"server","description":"Pulls a list of servers associated to forge account.","pluginName":"specter","pluginType":"core","aliases":[],"flags":{"output":{"name":"output","type":"option","char":"o","description":"Output file in which to register remote servers list."}},"args":[{"name":"id","description":"Forge ID for server which you are pulling information for.","required":true}]},"servers":{"id":"servers","description":"Pulls a list of servers associated to forge account.","pluginName":"specter","pluginType":"core","aliases":[],"flags":{"output":{"name":"output","type":"option","char":"o","description":"Output file in which to register remote servers list."}},"args":[]},"vps":{"id":"vps","description":"Returns the list of VPS provider registered to forge.","pluginName":"specter","pluginType":"core","aliases":[],"flags":{},"args":[]}}}